pandas_pcaxis/__init__.py
pandas_pcaxis/px_reader.py
pandas_pcaxis/pxweb_api.py
pandas_pcaxis/statfi_px_api.py
pandas_pcaxis-0.2.dist-info/LICENSE
pandas_pcaxis-0.2.dist-info/METADATA
pandas_pcaxis-0.2.dist-info/WHEEL
pandas_pcaxis-0.2.dist-info/top_level.txt
pandas_pcaxis-0.2.dist-info/RECORD
